{
    "Name": "Pomegranate Cranberry Yerba Mate Soda",
    "Description": "A carbonated version of Pomegranate Cranberry Yerba Mate.",
    "Category": "ArtisanGoods",
    "Edibility": 21,
    "EdibleIsDrink": true,
    "EdibleBuffs":
    {
        "Farming": 0,
        "Fishing": 0,
        "Mining": 0,
        "Luck": 0,
        "Foraging": 2,
        "MaxStamina": 0,
        "MagnetRadius": 0,
        "Speed": 0,
        "Defense": 0,
        "Attack": 0,
        "Duration": 300,
    },
    "Price": 900,
    "IsColored": false,
    "Recipe": null,

		
    
    "GiftTastes":
    {
        "Love": ["Caroline", "Harvey", "Leah", "Elliott"],
        "Like": ["Abigail", "Alex", "Clint", "Demetrius", "Dwarf", "Emily", "George", "Gus", "Haley", "Kent", "Krobus", "Lewis", "Linus", "Maru", "Marnie", "Pam", "Penny", "Pierre", "Robin", "Sam", "Sandy", "Sebastian", "Shane", "Willy", "Wizard"],
        
        "Neutral": ["Jas", "Vincent", "Leo"],
    },


    "NameLocalization":
    {
       // "es": "",
       // "ko": "",
       // "de": "",
        //"fr": "",
         // "hu": "",
         // "it": "",
        //"ja": "",
       // "pt": "",
        //"ru": "",
         // "tr": "",
       // "zh": "",
    },
    "DescriptionLocalization":
    {
        //"es": "",
        //"ko": "",
        //"de": "",
       // "fr": "",
         // "hu": "",
         // "it": "",
       // "ja": "",
        //"pt": "",
       // "ru": "",
         // "tr": "",
       // "zh": "",
    },
    
}